{
  "teamIds": {
    "Mexico": 16,
    "South Africa": 1531,
    "Korea Republic": 17,
    "Czechia": 770,
    "Canada": 5529,
    "Bosnia": 1113,
    "USA": 2384,
    "Paraguay": 2380,
    "Qatar": 1569,
    "Switzerland": 15,
    "Brazil": 6,
    "Morocco": 31,
    "Haiti": 2386,
    "Scotland": 1108,
    "Australia": 20,
    "Turkey": 777,
    "Germany": 25,
    "Curaçao": 5530,
    "Netherlands": 1118,
    "Japan": 12,
    "Côte d'Ivoire": 1501,
    "Ecuador": 2382,
    "Sweden": 5,
    "Tunisia": 28,
    "Spain": 9,
    "Cabo Verde": 1533,
    "Belgium": 1,
    "Egypt": 32,
    "Saudi Arabia": 23,
    "Uruguay": 7,
    "IR Iran": 22,
    "New Zealand": 4673,
    "France": 2,
    "Senegal": 13,
    "Iraq": 1567,
    "Norway": 1090,
    "Argentina": 26,
    "Algeria": 1532,
    "Austria": 775,
    "Jordan": 1548,
    "Portugal": 27,
    "DR Congo": 1508,
    "England": 10,
    "Croatia": 3,
    "Ghana": 1504,
    "Panama": 11,
    "Uzbekistan": 1568,
    "Colombia": 8
  },
  "teamTs": {
    "Mexico": "2026-06-30T16:38:02.852Z",
    "South Africa": "2026-06-30T16:38:03.200Z",
    "Korea Republic": "2026-06-30T16:38:03.894Z",
    "Czechia": "2026-06-30T16:38:04.248Z",
    "Canada": "2026-06-30T16:38:04.776Z",
    "Bosnia": "2026-06-30T16:38:05.124Z",
    "USA": "2026-06-30T16:38:05.490Z",
    "Paraguay": "2026-06-30T16:38:06.172Z",
    "Qatar": "2026-06-30T16:38:07.041Z",
    "Switzerland": "2026-06-30T16:38:07.389Z",
    "Brazil": "2026-06-30T16:38:08.265Z",
    "Morocco": "2026-06-30T16:38:08.624Z",
    "Haiti": "2026-06-30T16:38:09.147Z",
    "Scotland": "2026-06-30T16:38:09.517Z",
    "Australia": "2026-06-30T16:38:10.318Z",
    "Turkey": "2026-06-30T16:38:10.676Z",
    "Germany": "2026-06-30T16:38:11.017Z",
    "Curaçao": "2026-06-30T16:38:11.559Z",
    "Netherlands": "2026-06-30T16:38:11.911Z",
    "Japan": "2026-06-30T16:38:12.627Z",
    "Côte d'Ivoire": "2026-06-30T16:38:12.975Z",
    "Ecuador": "2026-06-30T16:38:13.652Z",
    "Sweden": "2026-06-30T16:38:13.998Z",
    "Tunisia": "2026-06-30T16:38:14.339Z",
    "Spain": "2026-06-30T16:38:14.856Z",
    "Cabo Verde": "2026-06-30T16:38:15.200Z",
    "Belgium": "2026-06-30T16:38:15.531Z",
    "Egypt": "2026-06-30T16:38:15.893Z",
    "Saudi Arabia": "2026-06-30T16:38:16.787Z",
    "Uruguay": "2026-06-30T16:38:17.814Z",
    "IR Iran": "2026-06-30T16:38:18.507Z",
    "New Zealand": "2026-06-30T16:38:18.847Z",
    "France": "2026-06-30T16:38:19.185Z",
    "Senegal": "2026-06-30T16:38:19.590Z",
    "Iraq": "2026-06-30T16:38:20.278Z",
    "Norway": "2026-06-30T16:38:20.612Z",
    "Argentina": "2026-06-30T16:38:21.290Z",
    "Algeria": "2026-06-30T16:38:21.657Z",
    "Austria": "2026-06-30T16:38:21.992Z",
    "Jordan": "2026-06-30T16:38:22.677Z",
    "Portugal": "2026-06-30T16:38:23.023Z",
    "DR Congo": "2026-06-30T16:38:23.369Z",
    "England": "2026-06-30T16:38:23.898Z",
    "Croatia": "2026-06-30T16:38:24.233Z",
    "Ghana": "2026-06-30T16:38:24.729Z",
    "Panama": "2026-06-30T16:38:25.235Z",
    "Uzbekistan": "2026-06-30T16:38:25.757Z",
    "Colombia": "2026-06-30T16:38:26.477Z"
  },
  "h2hTs": {
    "Mexico|South Africa": "2026-06-25T23:00:30.808Z",
    "Korea Republic|Czechia": "2026-06-25T23:00:31.237Z",
    "Canada|Bosnia": "2026-06-25T23:00:31.612Z",
    "USA|Paraguay": "2026-06-25T23:00:31.998Z",
    "Qatar|Switzerland": "2026-06-25T23:00:32.454Z",
    "Brazil|Morocco": "2026-06-25T23:00:32.862Z",
    "Haiti|Scotland": "2026-06-25T23:00:33.231Z",
    "Australia|Turkey": "2026-06-25T23:00:33.654Z",
    "Germany|Curaçao": "2026-06-25T23:00:34.054Z",
    "Netherlands|Japan": "2026-06-25T23:00:34.437Z",
    "Côte d'Ivoire|Ecuador": "2026-06-25T23:00:34.831Z",
    "Sweden|Tunisia": "2026-06-25T23:00:35.242Z",
    "Spain|Cabo Verde": "2026-06-25T23:00:35.627Z",
    "Belgium|Egypt": "2026-06-25T23:00:36.007Z",
    "Saudi Arabia|Uruguay": "2026-06-25T23:00:36.405Z",
    "IR Iran|New Zealand": "2026-06-25T23:00:36.786Z",
    "France|Senegal": "2026-06-25T23:00:37.163Z",
    "Iraq|Norway": "2026-06-25T23:00:37.545Z",
    "Argentina|Algeria": "2026-06-25T23:00:37.908Z",
    "Austria|Jordan": "2026-06-25T23:00:38.281Z",
    "Portugal|DR Congo": "2026-06-25T23:00:38.642Z",
    "England|Croatia": "2026-06-25T23:00:39.053Z",
    "Ghana|Panama": "2026-06-25T23:00:39.469Z",
    "Uzbekistan|Colombia": "2026-06-25T23:00:39.863Z",
    "Czechia|South Africa": "2026-06-25T23:00:40.232Z",
    "Switzerland|Bosnia": "2026-06-25T23:00:40.603Z",
    "Canada|Qatar": "2026-06-25T23:00:41.007Z",
    "Mexico|Korea Republic": "2026-06-25T23:00:41.495Z",
    "USA|Australia": "2026-06-25T23:00:41.902Z",
    "Scotland|Morocco": "2026-06-25T23:00:42.299Z",
    "Turkey|Paraguay": "2026-06-25T23:00:42.683Z",
    "Brazil|Haiti": "2026-06-25T23:00:43.054Z",
    "Netherlands|Sweden": "2026-06-25T23:00:43.457Z",
    "Germany|Côte d'Ivoire": "2026-06-25T23:00:43.839Z",
    "Ecuador|Curaçao": "2026-06-25T23:00:44.203Z",
    "Tunisia|Japan": "2026-06-25T23:00:44.570Z",
    "Spain|Saudi Arabia": "2026-06-25T23:00:44.941Z",
    "Belgium|IR Iran": "2026-06-25T23:00:45.324Z",
    "Uruguay|Cabo Verde": "2026-06-25T23:00:45.725Z",
    "New Zealand|Egypt": "2026-06-25T23:00:46.093Z",
    "Argentina|Austria": "2026-06-25T23:00:46.476Z",
    "France|Iraq": "2026-06-25T23:00:46.836Z",
    "Norway|Senegal": "2026-06-25T23:00:47.208Z",
    "Jordan|Algeria": "2026-06-25T23:00:47.602Z",
    "Portugal|Uzbekistan": "2026-06-25T23:00:47.953Z",
    "England|Ghana": "2026-06-25T23:00:48.311Z",
    "Panama|Croatia": "2026-06-25T23:00:48.725Z",
    "Colombia|DR Congo": "2026-06-25T23:00:49.101Z",
    "Switzerland|Canada": "2026-06-25T23:00:49.484Z",
    "Bosnia|Qatar": "2026-06-25T23:00:49.868Z",
    "Scotland|Brazil": "2026-06-25T23:00:50.237Z",
    "Morocco|Haiti": "2026-06-25T23:00:50.611Z",
    "Czechia|Mexico": "2026-06-25T23:00:50.988Z",
    "South Africa|Korea Republic": "2026-06-25T23:00:51.370Z",
    "Curaçao|Côte d'Ivoire": "2026-06-25T23:00:51.741Z",
    "Ecuador|Germany": "2026-06-25T23:00:52.454Z",
    "Japan|Sweden": "2026-06-25T23:00:53.168Z",
    "Tunisia|Netherlands": "2026-06-25T23:00:53.528Z",
    "Turkey|USA": "2026-06-25T23:00:53.908Z",
    "Paraguay|Australia": "2026-06-25T23:00:55.113Z",
    "Norway|France": "2026-06-25T23:00:56.202Z",
    "Senegal|Iraq": "2026-06-25T23:00:57.371Z",
    "Uruguay|Spain": "2026-06-25T23:00:58.465Z",
    "Cabo Verde|Saudi Arabia": "2026-06-25T23:00:59.521Z",
    "Egypt|IR Iran": "2026-06-25T23:01:00.838Z",
    "New Zealand|Belgium": "2026-06-25T23:01:03.023Z",
    "Panama|England": "2026-06-25T23:01:04.634Z",
    "Croatia|Ghana": "2026-06-25T23:01:06.066Z",
    "Colombia|Portugal": "2026-06-25T23:01:07.242Z",
    "DR Congo|Uzbekistan": "2026-06-25T23:01:08.384Z",
    "Algeria|Austria": "2026-06-25T23:01:09.456Z",
    "Jordan|Argentina": "2026-06-25T23:01:10.576Z",
    "South Africa|Canada": "2026-06-25T17:34:53.933Z",
    "Brazil|Japan": "2026-06-26T17:18:58.568Z",
    "Netherlands|Morocco": "2026-06-26T17:18:59.315Z",
    "Germany|Paraguay": "2026-06-28T10:16:39.692Z",
    "Côte d'Ivoire|Norway": "2026-06-28T10:16:41.337Z",
    "France|Sweden": "2026-06-28T10:16:42.242Z",
    "Mexico|Ecuador": "2026-06-28T10:16:43.140Z",
    "England|DR Congo": "2026-06-28T10:16:44.049Z",
    "Belgium|Senegal": "2026-06-28T10:16:44.934Z",
    "USA|Bosnia": "2026-06-28T10:16:45.815Z",
    "Spain|Austria": "2026-06-28T10:16:46.702Z",
    "Portugal|Croatia": "2026-06-28T10:16:47.592Z",
    "Switzerland|Algeria": "2026-06-28T10:16:48.487Z",
    "Australia|Egypt": "2026-06-28T10:16:49.368Z",
    "Argentina|Cabo Verde": "2026-06-28T10:16:50.263Z",
    "Colombia|Ghana": "2026-06-28T10:16:51.147Z"
  },
  "lineupTs": {
    "Mexico|South Africa": "2026-06-30T16:38:26.645Z",
    "Korea Republic|Czechia": "2026-06-30T16:38:26.813Z",
    "Canada|Bosnia": "2026-06-30T16:38:26.977Z",
    "USA|Paraguay": "2026-06-30T16:38:27.147Z",
    "Qatar|Switzerland": "2026-06-30T16:38:27.322Z",
    "Brazil|Morocco": "2026-06-30T16:38:27.492Z",
    "Haiti|Scotland": "2026-06-30T16:38:27.917Z",
    "Australia|Turkey": "2026-06-30T16:38:28.086Z",
    "Germany|Curaçao": "2026-06-30T16:38:28.252Z",
    "Netherlands|Japan": "2026-06-30T16:38:28.422Z",
    "Côte d'Ivoire|Ecuador": "2026-06-30T16:38:28.599Z",
    "Sweden|Tunisia": "2026-06-30T16:38:28.798Z",
    "Spain|Cabo Verde": "2026-06-30T16:38:28.981Z",
    "Belgium|Egypt": "2026-06-30T16:38:29.147Z",
    "Saudi Arabia|Uruguay": "2026-06-30T16:38:29.344Z",
    "IR Iran|New Zealand": "2026-06-30T16:38:29.511Z",
    "France|Senegal": "2026-06-30T16:38:29.681Z",
    "Iraq|Norway": "2026-06-30T16:38:29.847Z",
    "Argentina|Algeria": "2026-06-30T16:38:30.014Z",
    "Austria|Jordan": "2026-06-30T16:38:30.198Z",
    "Portugal|DR Congo": "2026-06-30T16:38:30.366Z",
    "England|Croatia": "2026-06-30T16:38:30.534Z",
    "Ghana|Panama": "2026-06-30T16:38:30.697Z",
    "Uzbekistan|Colombia": "2026-06-30T16:38:30.868Z",
    "Czechia|South Africa": "2026-06-30T16:38:31.287Z",
    "Switzerland|Bosnia": "2026-06-30T16:38:31.463Z",
    "Canada|Qatar": "2026-06-30T16:38:31.631Z",
    "Mexico|Korea Republic": "2026-06-30T16:38:31.813Z",
    "USA|Australia": "2026-06-30T16:38:31.998Z",
    "Scotland|Morocco": "2026-06-30T16:38:32.189Z",
    "Turkey|Paraguay": "2026-06-30T16:38:32.361Z",
    "Brazil|Haiti": "2026-06-30T16:38:32.536Z",
    "Netherlands|Sweden": "2026-06-30T16:38:32.712Z",
    "Germany|Côte d'Ivoire": "2026-06-30T16:38:32.880Z",
    "Ecuador|Curaçao": "2026-06-30T16:38:33.053Z",
    "Tunisia|Japan": "2026-06-30T16:38:33.229Z",
    "Spain|Saudi Arabia": "2026-06-30T16:38:33.396Z",
    "Belgium|IR Iran": "2026-06-30T16:38:33.563Z",
    "Uruguay|Cabo Verde": "2026-06-30T16:38:33.731Z",
    "New Zealand|Egypt": "2026-06-30T16:38:33.904Z",
    "Argentina|Austria": "2026-06-30T16:38:34.077Z",
    "France|Iraq": "2026-06-30T16:38:34.252Z",
    "Norway|Senegal": "2026-06-30T16:38:34.418Z",
    "Jordan|Algeria": "2026-06-30T16:38:34.589Z",
    "Portugal|Uzbekistan": "2026-06-30T16:38:34.757Z",
    "England|Ghana": "2026-06-30T16:38:34.923Z",
    "Panama|Croatia": "2026-06-30T16:38:35.091Z",
    "Colombia|DR Congo": "2026-06-30T16:38:35.261Z",
    "Switzerland|Canada": "2026-06-30T16:38:35.432Z",
    "Bosnia|Qatar": "2026-06-30T16:38:35.600Z",
    "Scotland|Brazil": "2026-06-30T16:38:35.784Z",
    "Morocco|Haiti": "2026-06-30T16:38:35.963Z",
    "Czechia|Mexico": "2026-06-30T16:38:36.139Z",
    "South Africa|Korea Republic": "2026-06-30T16:38:36.323Z",
    "Curaçao|Côte d'Ivoire": "2026-06-30T16:38:36.492Z",
    "Ecuador|Germany": "2026-06-30T16:38:36.663Z",
    "Japan|Sweden": "2026-06-30T16:38:36.828Z",
    "Tunisia|Netherlands": "2026-06-30T16:38:36.995Z",
    "Turkey|USA": "2026-06-30T16:38:37.163Z",
    "Paraguay|Australia": "2026-06-30T16:38:37.330Z",
    "Norway|France": "2026-06-30T16:38:37.499Z",
    "Senegal|Iraq": "2026-06-30T16:38:37.670Z",
    "Uruguay|Spain": "2026-06-30T16:38:37.840Z",
    "Cabo Verde|Saudi Arabia": "2026-06-30T16:38:38.013Z",
    "Egypt|IR Iran": "2026-06-30T16:38:38.191Z",
    "New Zealand|Belgium": "2026-06-30T16:38:38.359Z",
    "Panama|England": "2026-06-30T16:38:38.532Z",
    "Croatia|Ghana": "2026-06-30T16:38:38.698Z",
    "Colombia|Portugal": "2026-06-30T16:38:38.864Z",
    "DR Congo|Uzbekistan": "2026-06-30T16:38:39.028Z",
    "Algeria|Austria": "2026-06-30T16:38:39.193Z",
    "Jordan|Argentina": "2026-06-30T16:38:39.360Z",
    "South Africa|Canada": "2026-06-28T19:58:50.438Z",
    "Brazil|Japan": "2026-06-29T14:51:36.740Z",
    "Netherlands|Morocco": "2026-06-29T21:08:55.170Z",
    "Germany|Paraguay": "2026-06-29T21:08:54.371Z",
    "Côte d'Ivoire|Norway": "2026-06-30T16:38:39.529Z",
    "France|Sweden": "2026-06-30T16:38:40.394Z",
    "Mexico|Ecuador": "2026-06-30T16:38:41.236Z",
    "England|DR Congo": "2026-06-30T16:38:42.088Z",
    "Belgium|Senegal": "2026-06-30T16:38:43.002Z",
    "USA|Bosnia": "2026-06-30T16:38:43.843Z",
    "Spain|Austria": "2026-06-30T16:38:44.728Z",
    "Portugal|Croatia": "2026-06-30T16:38:45.573Z",
    "Switzerland|Algeria": "2026-06-30T16:38:46.447Z",
    "Australia|Egypt": "2026-06-30T16:38:47.295Z",
    "Argentina|Cabo Verde": "2026-06-30T16:38:48.150Z",
    "Colombia|Ghana": "2026-06-30T16:38:49.008Z"
  }
}